sharded_google_photos/backup/add_new_metadata.py
sharded_google_photos/backup/gphotos_backup.py
sharded_google_photos/backup/gphotos_backup_events.py
sharded_google_photos/backup/gphotos_uploader.py
sharded_google_photos/backup/gphotos_uploader_events.py
sharded_google_photos/backup/group_diffs_with_metadata.py
sharded_google_photos/backup/media_item_repository.py
sharded_google_photos/backup/shared_album_repository.py
sharded_google_photos/cleanup/events.py
sharded_google_photos/cleanup/gphotos_cleaner.py
sharded_google_photos/shared/gphotos_album_client.py
sharded_google_photos/shared/gphotos_client.py
sharded_google_photos/shared/gphotos_mediaitem_client.py
sharded_google_photos/shared/testing/fake_eventbus.py
sharded_google_photos/shared/testing/fake_gphotos_album_client.py
sharded_google_photos/shared/testing/fake_gphotos_client.py
sharded_google_photos/shared/testing/fake_gphotos_mediaitem_client.py
sharded_google_photos/shared/testing/fake_gphotos_repository.py
sharded_google_photos/shared/testing/mocked_saved_credentials_file.py
sharded_google_photos-0.2.4.dist-info/LICENSE
sharded_google_photos-0.2.4.dist-info/METADATA
sharded_google_photos-0.2.4.dist-info/WHEEL
sharded_google_photos-0.2.4.dist-info/RECORD
