Metadata-Version: 2.1
Name: sharded-google-photos
Version: 0.2.4
Summary: A tool to shard photos across multiple Google Photo accounts
License: GNU General Public License v3.0
Author: Emilio K
Author-email: e.kartonoe@gmail.com
Requires-Python: >=3.12,<4.0
Classifier: License :: Other/Proprietary License
Classifier: Programming Language :: Python :: 3
Classifier: Programming Language :: Python :: 3.12
Requires-Dist: backoff (>=2.2.1,<3.0.0)
Requires-Dist: event-bus (>=1.0.2,<2.0.0)
Requires-Dist: google-api-python-client (>=2.122.0,<3.0.0)
Requires-Dist: google-auth-oauthlib (>=1.2.0,<2.0.0)
Requires-Dist: python-magic (>=0.4.27,<0.5.0)
Requires-Dist: tqdm (>=4.66.2,<5.0.0)
